{
	"configurations" : 
	[
		{
			"directories" : 
			[
				{
					"build" : ".",
					"childIndexes" : 
					[
						1,
						2
					],
					"minimumCMakeVersion" : 
					{
						"string" : "2.8"
					},
					"projectIndex" : 0,
					"source" : "."
				},
				{
					"build" : "src",
					"minimumCMakeVersion" : 
					{
						"string" : "2.8"
					},
					"parentIndex" : 0,
					"projectIndex" : 0,
					"source" : "src",
					"targetIndexes" : 
					[
						0
					]
				},
				{
					"build" : "test",
					"minimumCMakeVersion" : 
					{
						"string" : "2.8"
					},
					"parentIndex" : 0,
					"projectIndex" : 0,
					"source" : "test",
					"targetIndexes" : 
					[
						1,
						2,
						3
					]
				}
			],
			"name" : "",
			"projects" : 
			[
				{
					"directoryIndexes" : 
					[
						0,
						1,
						2
					],
					"name" : "SLAM",
					"targetIndexes" : 
					[
						0,
						1,
						2,
						3
					]
				}
			],
			"targets" : 
			[
				{
					"directoryIndex" : 1,
					"id" : "SLAM::@145eef247bfb46b6828c",
					"jsonFile" : "target-SLAM-bc6dd5a0b72dc9c9a537.json",
					"name" : "SLAM",
					"projectIndex" : 0
				},
				{
					"directoryIndex" : 2,
					"id" : "run_vo::@36f028580bb02cc8272a",
					"jsonFile" : "target-run_vo-b97c858ec5cd7c12a445.json",
					"name" : "run_vo",
					"projectIndex" : 0
				},
				{
					"directoryIndex" : 2,
					"id" : "slamEnd::@36f028580bb02cc8272a",
					"jsonFile" : "target-slamEnd-43f4bd6715f5b719bec5.json",
					"name" : "slamEnd",
					"projectIndex" : 0
				},
				{
					"directoryIndex" : 2,
					"id" : "test::@36f028580bb02cc8272a",
					"jsonFile" : "target-test-8dc230f8721dd2188cc6.json",
					"name" : "test",
					"projectIndex" : 0
				}
			]
		}
	],
	"kind" : "codemodel",
	"paths" : 
	{
		"build" : "/home/park/Work/opencv_to_realsense2/project/build",
		"source" : "/home/park/Work/opencv_to_realsense2/project"
	},
	"version" : 
	{
		"major" : 2,
		"minor" : 1
	}
}
